fairmotion/__init__.py
fairmotion/core/__init__.py
fairmotion/core/motion.py
fairmotion/core/similarity.py
fairmotion/core/velocity.py
fairmotion/data/__init__.py
fairmotion/data/amass.py
fairmotion/data/amass_dip.py
fairmotion/data/asfamc.py
fairmotion/data/bvh.py
fairmotion/models/__init__.py
fairmotion/models/decoders.py
fairmotion/models/encoders.py
fairmotion/models/optimizer.py
fairmotion/models/rnn.py
fairmotion/models/seq2seq.py
fairmotion/models/transformer.py
fairmotion/motion/__init__.py
fairmotion/motion/motion.py
fairmotion/motion/similarity.py
fairmotion/motion/velocity.py
fairmotion/ops/__init__.py
fairmotion/ops/conversions.py
fairmotion/ops/math.py
fairmotion/ops/motion.py
fairmotion/ops/quaternion.py
fairmotion/processing/__init__.py
fairmotion/processing/operations.py
fairmotion/tasks/__init__.py
fairmotion/tasks/changepoint_detection/__init__.py
fairmotion/tasks/changepoint_detection/detect.py
fairmotion/tasks/clustering/__init__.py
fairmotion/tasks/clustering/clustering.py
fairmotion/tasks/clustering/generate_features.py
fairmotion/tasks/clustering/split_bvh.py
fairmotion/tasks/clustering/test_generate_features.py
fairmotion/tasks/clustering/features/__init__.py
fairmotion/tasks/clustering/features/kinetic.py
fairmotion/tasks/clustering/features/manual.py
fairmotion/tasks/clustering/features/thresholds.py
fairmotion/tasks/clustering/features/utils.py
fairmotion/tasks/motion_graph/__init__.py
fairmotion/tasks/motion_graph/main.py
fairmotion/tasks/motion_graph/motion_graph.py
fairmotion/tasks/motion_prediction/__init__.py
fairmotion/tasks/motion_prediction/dataset.py
fairmotion/tasks/motion_prediction/generate.py
fairmotion/tasks/motion_prediction/metrics.py
fairmotion/tasks/motion_prediction/preprocess.py
fairmotion/tasks/motion_prediction/test.py
fairmotion/tasks/motion_prediction/training.py
fairmotion/tasks/motion_prediction/utils.py
fairmotion/utils/__init__.py
fairmotion/utils/constants.py
fairmotion/utils/conversions.py
fairmotion-0.0.4.dist-info/LICENSE
fairmotion-0.0.4.dist-info/METADATA
fairmotion-0.0.4.dist-info/WHEEL
fairmotion-0.0.4.dist-info/top_level.txt
fairmotion-0.0.4.dist-info/RECORD
